custom_tree_classifier/__init__.py
custom_tree_classifier/metrics/__init__.py
custom_tree_classifier/metrics/entropy.py
custom_tree_classifier/metrics/gini.py
custom_tree_classifier/metrics/metric_base.py
custom_tree_classifier/metrics/misclassification.py
custom_tree_classifier/metrics/mse.py
custom_tree_classifier/metrics/weighted_entropy.py
custom_tree_classifier/metrics/weighted_gini.py
custom_tree_classifier/models/__init__.py
custom_tree_classifier/models/decision_tree.py
custom_tree_classifier/models/random_forest.py
custom_tree_classifier-1.0.4.dist-info/LICENSE
custom_tree_classifier-1.0.4.dist-info/METADATA
custom_tree_classifier-1.0.4.dist-info/WHEEL
custom_tree_classifier-1.0.4.dist-info/top_level.txt
custom_tree_classifier-1.0.4.dist-info/RECORD
