Metadata-Version: 2.1
Name: custom-tree-classifier
Version: 1.0.4
Summary: A package for building decision trees and random forests with custom splitting criteria.
Home-page: https://github.com/AntoinePinto/custom-tree-classifier
Author: Antoine PINTO
Author-email: antoine.pinto1@outlook.fr
License: MIT
Project-URL: Source Code, https://github.com/AntoinePinto/custom-tree-classifier
Keywords: decision tree,random forest,machine learning,classification,custom splitting criteria
Requires-Python: >=3.10
License-File: LICENSE
Requires-Dist: numpy>=1.19.0
Requires-Dist: tqdm>=4.50.0
